[
    {
        "id": "272458880",
        "name": "CHILL BRO",
        "swissWins": 1,
        "top16": false,
        "winnersWins": 0,
        "losersWins": 0,
        "first": false,
        "second": false,
        "third": false,
        "points": 15,
        "rank": -1
    },
    {
        "id": "272458865",
        "name": "AARON",
        "swissWins": 4,
        "top16": true,
        "winnersWins": 1,
        "losersWins": 3,
        "first": false,
        "second": false,
        "third": false,
        "points": 65,
        "rank": -1
    },
    {
        "id": "272458882",
        "name": "MATT",
        "swissWins": 1,
        "top16": false,
        "winnersWins": 0,
        "losersWins": 0,
        "first": false,
        "second": false,
        "third": false,
        "points": 15,
        "rank": -1
    },
    {
        "id": "272458858",
        "name": "TANTAN",
        "swissWins": 4,
        "top16": true,
        "winnersWins": 0,
        "losersWins": 1,
        "first": false,
        "second": false,
        "third": false,
        "points": 45,
        "rank": -1
    },
    {
        "id": "272458870",
        "name": "DANIEL T",
        "swissWins": 0,
        "top16": false,
        "winnersWins": 0,
        "losersWins": 0,
        "first": false,
        "second": false,
        "third": false,
        "points": 10,
        "rank": -1
    },
    {
        "id": "272458875",
        "name": "PAUL",
        "swissWins": 3,
        "top16": true,
        "winnersWins": 1,
        "losersWins": 2,
        "first": false,
        "second": false,
        "third": false,
        "points": 55,
        "rank": -1
    },
    {
        "id": "272458866",
        "name": "LAZAROID",
        "swissWins": 1,
        "top16": false,
        "winnersWins": 0,
        "losersWins": 0,
        "first": false,
        "second": false,
        "third": false,
        "points": 15,
        "rank": -1
    },
    {
        "id": "272458881",
        "name": "GWEN",
        "swissWins": 4,
        "top16": true,
        "winnersWins": 0,
        "losersWins": 1,
        "first": false,
        "second": false,
        "third": false,
        "points": 45,
        "rank": -1
    },
    {
        "id": "272458884",
        "name": "ADI",
        "swissWins": 3,
        "top16": false,
        "winnersWins": 0,
        "losersWins": 0,
        "first": false,
        "second": false,
        "third": false,
        "points": 25,
        "rank": -1
    },
    {
        "id": "272458889",
        "name": "SHIRO",
        "swissWins": 3,
        "top16": false,
        "winnersWins": 0,
        "losersWins": 0,
        "first": false,
        "second": false,
        "third": false,
        "points": 25,
        "rank": -1
    },
    {
        "id": "272458883",
        "name": "3SH",
        "swissWins": 2,
        "top16": false,
        "winnersWins": 0,
        "losersWins": 0,
        "first": false,
        "second": false,
        "third": false,
        "points": 20,
        "rank": -1
    },
    {
        "id": "272458867",
        "name": "NHIMRODD",
        "swissWins": 5,
        "top16": true,
        "winnersWins": 1,
        "losersWins": 1,
        "first": false,
        "second": false,
        "third": false,
        "points": 80,
        "rank": -1
    },
    {
        "id": "272458887",
        "name": "BBBBBBROAD",
        "swissWins": 2,
        "top16": false,
        "winnersWins": 0,
        "losersWins": 0,
        "first": false,
        "second": false,
        "third": false,
        "points": 20,
        "rank": -1
    },
    {
        "id": "272458863",
        "name": "YOMI",
        "swissWins": 0,
        "top16": false,
        "winnersWins": 0,
        "losersWins": 0,
        "first": false,
        "second": false,
        "third": false,
        "points": 10,
        "rank": -1
    },
    {
        "id": "272458868",
        "name": "CHRIS A",
        "swissWins": 2,
        "top16": false,
        "winnersWins": 0,
        "losersWins": 0,
        "first": false,
        "second": false,
        "third": false,
        "points": 20,
        "rank": -1
    },
    {
        "id": "272458861",
        "name": "JACOB",
        "swissWins": 3,
        "top16": false,
        "winnersWins": 0,
        "losersWins": 0,
        "first": false,
        "second": false,
        "third": false,
        "points": 25,
        "rank": -1
    },
    {
        "id": "272458886",
        "name": "RUSS",
        "swissWins": 4,
        "top16": true,
        "winnersWins": 2,
        "losersWins": 0,
        "first": false,
        "second": false,
        "third": false,
        "points": 60,
        "rank": -1
    },
    {
        "id": "272458855",
        "name": "DR RUBTAH",
        "swissWins": 2,
        "top16": false,
        "winnersWins": 0,
        "losersWins": 0,
        "first": false,
        "second": false,
        "third": false,
        "points": 20,
        "rank": -1
    },
    {
        "id": "272458873",
        "name": "JULES",
        "swissWins": 3,
        "top16": true,
        "winnersWins": 0,
        "losersWins": 1,
        "first": false,
        "second": false,
        "third": false,
        "points": 40,
        "rank": -1
    },
    {
        "id": "272458885",
        "name": "CASTER",
        "swissWins": 2,
        "top16": false,
        "winnersWins": 0,
        "losersWins": 0,
        "first": false,
        "second": false,
        "third": false,
        "points": 20,
        "rank": -1
    },
    {
        "id": "272458888",
        "name": "STEVEN",
        "swissWins": 1,
        "top16": false,
        "winnersWins": 0,
        "losersWins": 0,
        "first": false,
        "second": false,
        "third": false,
        "points": 15,
        "rank": -1
    },
    {
        "id": "272458869",
        "name": "WREKCY",
        "swissWins": 4,
        "top16": true,
        "winnersWins": 1,
        "losersWins": 1,
        "first": false,
        "second": false,
        "third": false,
        "points": 55,
        "rank": -1
    },
    {
        "id": "272458859",
        "name": "BONESHELLY",
        "swissWins": 2,
        "top16": false,
        "winnersWins": 0,
        "losersWins": 0,
        "first": false,
        "second": false,
        "third": false,
        "points": 20,
        "rank": -1
    },
    {
        "id": "272458872",
        "name": "R VN",
        "swissWins": 3,
        "top16": true,
        "winnersWins": 0,
        "losersWins": 1,
        "first": false,
        "second": false,
        "third": false,
        "points": 40,
        "rank": -1
    },
    {
        "id": "272458877",
        "name": "JAREN JAMES",
        "swissWins": 2,
        "top16": false,
        "winnersWins": 0,
        "losersWins": 0,
        "first": false,
        "second": false,
        "third": false,
        "points": 20,
        "rank": -1
    },
    {
        "id": "272458864",
        "name": "JEFF G",
        "swissWins": 2,
        "top16": false,
        "winnersWins": 0,
        "losersWins": 0,
        "first": false,
        "second": false,
        "third": false,
        "points": 20,
        "rank": -1
    },
    {
        "id": "272458876",
        "name": "AKUMA",
        "swissWins": 3,
        "top16": false,
        "winnersWins": 0,
        "losersWins": 0,
        "first": false,
        "second": false,
        "third": false,
        "points": 25,
        "rank": -1
    },
    {
        "id": "272458871",
        "name": "VICKI",
        "swissWins": 0,
        "top16": false,
        "winnersWins": 0,
        "losersWins": 0,
        "first": false,
        "second": false,
        "third": false,
        "points": 10,
        "rank": -1
    },
    {
        "id": "272458857",
        "name": "JESSICA",
        "swissWins": 4,
        "top16": true,
        "winnersWins": 3,
        "losersWins": 1,
        "first": false,
        "second": true,
        "third": false,
        "points": 105,
        "rank": -1
    },
    {
        "id": "272458856",
        "name": "REN",
        "swissWins": 3,
        "top16": false,
        "winnersWins": 0,
        "losersWins": 0,
        "first": false,
        "second": false,
        "third": false,
        "points": 25,
        "rank": -1
    },
    {
        "id": "272458879",
        "name": "LEO",
        "swissWins": 2,
        "top16": false,
        "winnersWins": 0,
        "losersWins": 0,
        "first": false,
        "second": false,
        "third": false,
        "points": 20,
        "rank": -1
    },
    {
        "id": "272458862",
        "name": "KYOYA",
        "swissWins": 4,
        "top16": true,
        "winnersWins": 2,
        "losersWins": 2,
        "first": false,
        "second": false,
        "third": true,
        "points": 90,
        "rank": -1
    },
    {
        "id": "272458874",
        "name": "NEIL",
        "swissWins": 3,
        "top16": true,
        "winnersWins": 5,
        "losersWins": 0,
        "first": true,
        "second": false,
        "third": false,
        "points": 135,
        "rank": -1
    },
    {
        "id": "272458878",
        "name": "GUAR",
        "swissWins": 2,
        "top16": false,
        "winnersWins": 0,
        "losersWins": 0,
        "first": false,
        "second": false,
        "third": false,
        "points": 20,
        "rank": -1
    },
    {
        "id": "272458860",
        "name": "MR PREZ",
        "swissWins": 1,
        "top16": false,
        "winnersWins": 0,
        "losersWins": 0,
        "first": false,
        "second": false,
        "third": false,
        "points": 15,
        "rank": -1
    }
]