[
    {
        "id": "268811612",
        "name": "ADZ",
        "swissWins": 2,
        "top16": false,
        "winnersWins": 0,
        "losersWins": 0,
        "first": false,
        "second": false,
        "third": false,
        "points": 20,
        "rank": -1
    },
    {
        "id": "268811611",
        "name": "JONATHAN V",
        "swissWins": 3,
        "top16": false,
        "winnersWins": 0,
        "losersWins": 0,
        "first": false,
        "second": false,
        "third": false,
        "points": 25,
        "rank": -1
    },
    {
        "id": "268811603",
        "name": "FOXOF2FACES",
        "swissWins": 4,
        "top16": true,
        "winnersWins": 5,
        "losersWins": 1,
        "first": true,
        "second": false,
        "third": false,
        "points": 145,
        "rank": -1
    },
    {
        "id": "268811604",
        "name": "IRIS",
        "swissWins": 1,
        "top16": false,
        "winnersWins": 0,
        "losersWins": 0,
        "first": false,
        "second": false,
        "third": false,
        "points": 15,
        "rank": -1
    },
    {
        "id": "268811626",
        "name": "JEFF G",
        "swissWins": 2,
        "top16": false,
        "winnersWins": 0,
        "losersWins": 0,
        "first": false,
        "second": false,
        "third": false,
        "points": 20,
        "rank": -1
    },
    {
        "id": "268811636",
        "name": "PANDA",
        "swissWins": 2,
        "top16": false,
        "winnersWins": 0,
        "losersWins": 0,
        "first": false,
        "second": false,
        "third": false,
        "points": 20,
        "rank": -1
    },
    {
        "id": "268811591",
        "name": "TYLER S",
        "swissWins": 4,
        "top16": true,
        "winnersWins": 2,
        "losersWins": 0,
        "first": false,
        "second": false,
        "third": false,
        "points": 60,
        "rank": -1
    },
    {
        "id": "268811599",
        "name": "NEIL",
        "swissWins": 2,
        "top16": false,
        "winnersWins": 0,
        "losersWins": 0,
        "first": false,
        "second": false,
        "third": false,
        "points": 20,
        "rank": -1
    },
    {
        "id": "268811620",
        "name": "JESSICA",
        "swissWins": 3,
        "top16": true,
        "winnersWins": 1,
        "losersWins": 1,
        "first": false,
        "second": false,
        "third": false,
        "points": 50,
        "rank": -1
    },
    {
        "id": "268811602",
        "name": "Z3RO",
        "swissWins": 1,
        "top16": false,
        "winnersWins": 0,
        "losersWins": 0,
        "first": false,
        "second": false,
        "third": false,
        "points": 15,
        "rank": -1
    },
    {
        "id": "268811638",
        "name": "SSRAY",
        "swissWins": 2,
        "top16": false,
        "winnersWins": 0,
        "losersWins": 0,
        "first": false,
        "second": false,
        "third": false,
        "points": 20,
        "rank": -1
    },
    {
        "id": "268811606",
        "name": "ZACH",
        "swissWins": 2,
        "top16": false,
        "winnersWins": 0,
        "losersWins": 0,
        "first": false,
        "second": false,
        "third": false,
        "points": 20,
        "rank": -1
    },
    {
        "id": "268811615",
        "name": "ONEZ",
        "swissWins": 2,
        "top16": false,
        "winnersWins": 0,
        "losersWins": 0,
        "first": false,
        "second": false,
        "third": false,
        "points": 20,
        "rank": -1
    },
    {
        "id": "268811610",
        "name": "SHELBY",
        "swissWins": 0,
        "top16": false,
        "winnersWins": 0,
        "losersWins": 0,
        "first": false,
        "second": false,
        "third": false,
        "points": 10,
        "rank": -1
    },
    {
        "id": "268811601",
        "name": "JULES",
        "swissWins": 3,
        "top16": false,
        "winnersWins": 0,
        "losersWins": 0,
        "first": false,
        "second": false,
        "third": false,
        "points": 25,
        "rank": -1
    }
]

[
    "ADZ",
    "JONATHAN V",
    "FOXOF2FACES",
    "IRIS",
    "JEFF G",
    "PANDA",
    "TYLER S",
    "NEIL",
    "JESSICA",
    "Z3RO",
    "SSRAY",
    "ZACH",
    "ONEZ",
    "SHELBY",
    "JULES"
]

[
    {
        "id": "271322390",
        "name": "SUGOI",
        "swissWins": 1,
        "top16": false,
        "winnersWins": 0,
        "losersWins": 0,
        "first": false,
        "second": false,
        "third": false,
        "points": 15,
        "rank": -1
    },
    {
        "id": "271322389",
        "name": "MULTI",
        "swissWins": 3,
        "top16": true,
        "winnersWins": 2,
        "losersWins": 0,
        "first": false,
        "second": false,
        "third": false,
        "points": 55,
        "rank": -1
    },
    {
        "id": "271322406",
        "name": "DANIEL T",
        "swissWins": 2,
        "top16": false,
        "winnersWins": 0,
        "losersWins": 0,
        "first": false,
        "second": false,
        "third": false,
        "points": 20,
        "rank": -1
    },
    {
        "id": "271322412",
        "name": "ADZ",
        "swissWins": 1,
        "top16": false,
        "winnersWins": 0,
        "losersWins": 0,
        "first": false,
        "second": false,
        "third": false,
        "points": 15,
        "rank": -1
    },
    {
        "id": "271322382",
        "name": "JULES",
        "swissWins": 0,
        "top16": false,
        "winnersWins": 0,
        "losersWins": 0,
        "first": false,
        "second": false,
        "third": false,
        "points": 10,
        "rank": -1
    },
    {
        "id": "271322426",
        "name": "SKETCHI",
        "swissWins": 2,
        "top16": false,
        "winnersWins": 0,
        "losersWins": 0,
        "first": false,
        "second": false,
        "third": false,
        "points": 20,
        "rank": -1
    },
    {
        "id": "271322395",
        "name": "ONEZ",
        "swissWins": 3,
        "top16": false,
        "winnersWins": 0,
        "losersWins": 0,
        "first": false,
        "second": false,
        "third": false,
        "points": 25,
        "rank": -1
    },
    {
        "id": "271322417",
        "name": "JUST VERN",
        "swissWins": 2,
        "top16": false,
        "winnersWins": 0,
        "losersWins": 0,
        "first": false,
        "second": false,
        "third": false,
        "points": 20,
        "rank": -1
    },
    {
        "id": "271322404",
        "name": "JULIAN",
        "swissWins": 2,
        "top16": false,
        "winnersWins": 0,
        "losersWins": 0,
        "first": false,
        "second": false,
        "third": false,
        "points": 20,
        "rank": -1
    },
    {
        "id": "271322420",
        "name": "LEO",
        "swissWins": 3,
        "top16": false,
        "winnersWins": 0,
        "losersWins": 0,
        "first": false,
        "second": false,
        "third": false,
        "points": 25,
        "rank": -1
    },
    {
        "id": "271322416",
        "name": "MAC",
        "swissWins": 2,
        "top16": false,
        "winnersWins": 0,
        "losersWins": 0,
        "first": false,
        "second": false,
        "third": false,
        "points": 20,
        "rank": -1
    },
    {
        "id": "271322421",
        "name": "MATHEW S",
        "swissWins": 3,
        "top16": false,
        "winnersWins": 0,
        "losersWins": 0,
        "first": false,
        "second": false,
        "third": false,
        "points": 25,
        "rank": -1
    },
    {
        "id": "271322380",
        "name": "NEIL",
        "swissWins": 4,
        "top16": false,
        "winnersWins": 0,
        "losersWins": 0,
        "first": false,
        "second": false,
        "third": false,
        "points": 30,
        "rank": -1
    },
    {
        "id": "271322422",
        "name": "DIEGO",
        "swissWins": 4,
        "top16": true,
        "winnersWins": 1,
        "losersWins": 1,
        "first": false,
        "second": false,
        "third": false,
        "points": 55,
        "rank": -1
    }
]

[
    "SUGOI",
    "MULTI",
    "DANIEL T",
    "ADZ",
    "JULES",
    "SKETCHI",
    "ONEZ",
    "JUST VERN",
    "JULIAN",
    "LEO",
    "MAC",
    "MATHEW S",
    "NEIL",
    "DIEGO"
]